spyders_density-0.1.0.dist-info/METADATA
spyders_density-0.1.0.dist-info/WHEEL
spyders_density-0.1.0.dist-info/license_files/LICENCE.md
spyders/__init__.py
spyders/epanechnikov.py
spyders/mbe.py
spyders/spyders.pypy310-pp73-s390x-linux-gnu.so
spyders_density-0.1.0.dist-info/RECORD
