Metadata-Version: 2.3
Name: spyders_density
Version: 0.1.0
Classifier: Programming Language :: Rust
Classifier: Programming Language :: Python :: Implementation :: CPython
Classifier: Programming Language :: Python :: Implementation :: PyPy
License-File: LICENCE.md
Requires-Python: >=3.8
